test_blablababa/__init__.py
test_blablababa-0.3.dist-info/METADATA
test_blablababa-0.3.dist-info/WHEEL
test_blablababa-0.3.dist-info/entry_points.txt
test_blablababa-0.3.dist-info/top_level.txt
test_blablababa-0.3.dist-info/RECORD
