Metadata-Version: 2.1
Name: test-blablababa
Version: 0.3
Summary: A fake package
Author: practiccollie
Author-email: practiccollie@gmail.com
